segretini_matplottini/__init__.py
segretini_matplottini/py.typed
segretini_matplottini/plot/__init__.py
segretini_matplottini/plot/barplot.py
segretini_matplottini/plot/binary_classification.py
segretini_matplottini/plot/correlation_scatterplot.py
segretini_matplottini/plot/ridgeplot.py
segretini_matplottini/plot/roofline.py
segretini_matplottini/plot/timeseries.py
segretini_matplottini/utils/__init__.py
segretini_matplottini/utils/colors.py
segretini_matplottini/utils/constants.py
segretini_matplottini/utils/data.py
segretini_matplottini/utils/legend.py
segretini_matplottini/utils/plot.py
segretini_matplottini-0.4.0.dist-info/LICENSE
segretini_matplottini-0.4.0.dist-info/METADATA
segretini_matplottini-0.4.0.dist-info/WHEEL
segretini_matplottini-0.4.0.dist-info/top_level.txt
segretini_matplottini-0.4.0.dist-info/RECORD
