Metadata-Version: 2.1
Name: segretini-matplottini
Version: 0.4.0
Summary: Colorful recipes and utilities for Matplolib and Seaborn, to create publication-ready plots
Author-email: Alberto Parravicini <alberto.parravicini@polimi.it>
License: MIT License
Requires-Python: >=3.9
License-File: LICENSE
Requires-Dist: seaborn >=0.13.0
Requires-Dist: scipy >=1.3
Requires-Dist: statsmodels >=0.10
Requires-Dist: scikit-learn >=1.1.2
Requires-Dist: jaxtyping >=0.2.20
Requires-Dist: matplotlib >=3.8.0
Requires-Dist: pandas-stubs >=2.1.1
Provides-Extra: dev
Requires-Dist: black >=23.7 ; extra == 'dev'
Requires-Dist: isort >=5.12.0 ; extra == 'dev'
Requires-Dist: ruff >=0.1.1 ; extra == 'dev'
Requires-Dist: pre-commit >=3.3.3 ; extra == 'dev'
Requires-Dist: pytest >=7.4.0 ; extra == 'dev'
Requires-Dist: mypy >=1.6.1 ; extra == 'dev'
Requires-Dist: build >=0.10.0 ; extra == 'dev'
Requires-Dist: twine >=4.0.2 ; extra == 'dev'
Provides-Extra: notebook
Requires-Dist: notebook >=7.0.1 ; extra == 'notebook'
